sample_pkg/__init__.py
sample_pkg-0.0.1a1.data/data/my_data/data_file
sample_pkg-0.0.1a1.dist-info/LICENSE
sample_pkg-0.0.1a1.dist-info/METADATA
sample_pkg-0.0.1a1.dist-info/WHEEL
sample_pkg-0.0.1a1.dist-info/entry_points.txt
sample_pkg-0.0.1a1.dist-info/top_level.txt
sample_pkg-0.0.1a1.dist-info/RECORD
